peak_bot/__init__.py
peak_bot/__main__.py
peak_bot/peak_bot.py
peak_bot/antenna/__init__.py
peak_bot/antenna/bing_transcriber.py
peak_bot/antenna/google_transcriber.py
peak_bot/antenna/peak_connection.py
peak_bot/body/__init__.py
peak_bot/brain/__init__.py
peak_bot/brain/db_memory/__init__.py
peak_bot/brain/db_memory/database.py
peak_bot/brain/db_memory/queries.py
peak_bot/brain/db_memory/data_types/__init__.py
peak_bot/brain/db_memory/data_types/call.py
peak_bot/brain/db_memory/data_types/combo.py
peak_bot/brain/db_memory/data_types/command.py
peak_bot/brain/db_memory/data_types/external_module.py
peak_bot/brain/db_memory/data_types/imprt.py
peak_bot/brain/db_memory/data_types/language.py
peak_bot/brain/db_memory/data_types/module.py
peak_bot/brain/db_memory/data_types/word.py
peak_bot/brain/fs_memory/__init__.py
peak_bot/brain/fs_memory/file_handler.py
peak_bot/brain/processing/__init__.py
peak_bot/brain/processing/command_finder.py
peak_bot/brain/processing/executor.py
peak_bot/ears/__init__.py
peak_bot/ears/input_control.py
peak_bot/ears/listener.py
peak_bot/modules/__init__.py
peak_bot/modules/testprint.py
peak_bot/peak_data/configuration/audio_base.json
peak_bot/peak_data/configuration/lang_base.json
peak_bot/peak_data/configuration/settings.json
peak_bot/peak_data/library/core.json
peak_bot/peak_data/library/file_system.json
peak_bot/peak_data/library/networking.json
peak_bot/peak_data/library/core/append_to_file.json
peak_bot/peak_data/library/core/write_to_file.json
peak_bot/peak_data/library/file_system/copy.json
peak_bot/peak_data/library/networking/ping.json
peak_bot/tongue/__init__.py
peak_bot/tongue/output_control.py
peak_bot-1.0.1b4.data/data/peak_data/configuration/audio_base.json
peak_bot-1.0.1b4.data/data/peak_data/configuration/lang_base.json
peak_bot-1.0.1b4.data/data/peak_data/configuration/settings.json
peak_bot-1.0.1b4.data/data/peak_data/library/core.json
peak_bot-1.0.1b4.dist-info/METADATA
peak_bot-1.0.1b4.dist-info/RECORD
peak_bot-1.0.1b4.dist-info/WHEEL
peak_bot-1.0.1b4.dist-info/entry_points.txt
peak_bot-1.0.1b4.dist-info/top_level.txt
