Metadata-Version: 2.1
Name: peak-bot
Version: 1.0.1b4
Summary: Lightweight, simple, speech-to-text-oriented bot.
Home-page: https://github.com/doriclazar/peak_bot
Author: Lazar Doric
Author-email: doriclazar@gmail.com
License: UNKNOWN
Project-URL: Bug Reports, https://github.com/doriclazar/peak_bot/issues
Project-URL: Source, https://github.com/doriclazar/peak_bot/
Keywords: peak bots
Platform: UNKNOWN
Classifier: Development Status :: 4 - Beta
Classifier: Intended Audience :: End Users/Desktop
Classifier: Operating System :: Microsoft :: Windows
Classifier: Operating System :: POSIX :: Linux
Classifier: Topic :: Home Automation
Classifier: Topic :: Office/Business
Classifier: License :: OSI Approved :: Apache Software License
Classifier: Programming Language :: Python :: 3.6
Requires-Dist: pyaudio
Requires-Dist: google-cloud-speech
